mincepy_gui/__init__.py
mincepy_gui/action_controllers.py
mincepy_gui/actioners.py
mincepy_gui/columns.py
mincepy_gui/common.py
mincepy_gui/db.py
mincepy_gui/entry_details.py
mincepy_gui/entry_table.py
mincepy_gui/executors.py
mincepy_gui/extend.py
mincepy_gui/main.py
mincepy_gui/main_controllers.py
mincepy_gui/plugins.py
mincepy_gui/query.py
mincepy_gui/types_controller.py
mincepy_gui/utils.py
mincepy_gui/version.py
mincepy_gui/res/loading-small.gif
mincepy_gui/res/logo.svg
mincepy_gui/res/mainwindow.ui
mincepy_gui-0.3.7.dist-info/METADATA
mincepy_gui-0.3.7.dist-info/WHEEL
mincepy_gui-0.3.7.dist-info/entry_points.txt
mincepy_gui-0.3.7.dist-info/top_level.txt
mincepy_gui-0.3.7.dist-info/RECORD
